swafi/__init__.py
swafi/config.py
swafi/damages.py
swafi/damages_gvz.py
swafi/damages_mobiliar.py
swafi/domain.py
swafi/events.py
swafi/impact.py
swafi/impact_basic_options.py
swafi/impact_cnn.py
swafi/impact_cnn_data_generator.py
swafi/impact_cnn_model.py
swafi/impact_cnn_options.py
swafi/impact_dl.py
swafi/impact_dl_data_generator.py
swafi/impact_dl_options.py
swafi/impact_lr.py
swafi/impact_rf.py
swafi/impact_rf_options.py
swafi/impact_thr.py
swafi/impact_tx.py
swafi/impact_tx_data_generator.py
swafi/impact_tx_model.py
swafi/impact_tx_options.py
swafi/precip.py
swafi/precip_archive.py
swafi/precip_combiprecip.py
swafi/precip_forecast.py
swafi/precip_icon.py
swafi/utils/__init__.py
swafi/utils/optuna.py
swafi/utils/plotting.py
swafi/utils/spatial.py
swafi/utils/verification.py
swafi-0.2.0.dist-info/METADATA
swafi-0.2.0.dist-info/WHEEL
swafi-0.2.0.dist-info/top_level.txt
swafi-0.2.0.dist-info/RECORD
