Metadata-Version: 2.4
Name: swafi
Version: 0.2.0
Summary: Surface Water Flood Impact
Author: Pascal Horton
Author-email: pascal.horton@unibe.ch
License: MIT
Project-URL: Source Code, https://github.com/pascalhorton/surface-water-flood-impact
Project-URL: Bug Tracker, https://github.com/pascalhorton/surface-water-flood-impact/issues
Classifier: Programming Language :: Python
Classifier: Programming Language :: Python :: 3
Classifier: License :: OSI Approved :: MIT License
Requires-Python: >=3.8
Requires-Dist: numpy
Requires-Dist: PyYAML
Requires-Dist: pandas==2.*
Requires-Dist: rasterio
Requires-Dist: tqdm
Requires-Dist: pyarrow
Requires-Dist: scikit-learn
Requires-Dist: tensorflow
Requires-Dist: keras
Requires-Dist: xarray
Requires-Dist: dask
Requires-Dist: netcdf4
Requires-Dist: rioxarray
Provides-Extra: test
Requires-Dist: pytest>=6.0; extra == "test"
Dynamic: author
Dynamic: author-email
Dynamic: classifier
Dynamic: description
Dynamic: description-content-type
Dynamic: license
Dynamic: project-url
Dynamic: provides-extra
Dynamic: requires-dist
Dynamic: requires-python
Dynamic: summary
